durationstring.py
durationstring-1.2.3.dist-info/LICENSE
durationstring-1.2.3.dist-info/METADATA
durationstring-1.2.3.dist-info/WHEEL
durationstring-1.2.3.dist-info/top_level.txt
durationstring-1.2.3.dist-info/RECORD
